cockgrabber/__init__.py
cockgrabber/chumba.py
cockgrabber/gp.py
cockgrabber/pulsz.py
cockgrabber-1.81.dist-info/LICENSE
cockgrabber-1.81.dist-info/METADATA
cockgrabber-1.81.dist-info/WHEEL
cockgrabber-1.81.dist-info/top_level.txt
cockgrabber-1.81.dist-info/RECORD
