Metadata-Version: 2.1
Name: cockgrabber
Version: 1.81
Summary: grab cocks
Author: gravitas
Author-email: yourmom@gmail.com
License-File: LICENSE
Requires-Dist: undetected-chromedriver
Requires-Dist: 2captcha-python
Requires-Dist: selenium
Requires-Dist: psycopg2
Requires-Dist: pytesseract
